rcpann/__init__.py
rcpann/rcpann.py
rcpann/ann_model/geomag_2012_2018.csv
rcpann/ann_model/p_121_keV.h5
rcpann/ann_model/p_148_keV.h5
rcpann/ann_model/p_181_keV.h5
rcpann/ann_model/p_220_keV.h5
rcpann/ann_model/p_269_keV.h5
rcpann/ann_model/p_328_keV.h5
rcpann/ann_model/p_400_keV.h5
rcpann/ann_model/p_45_keV.h5
rcpann/ann_model/p_489_keV.h5
rcpann/ann_model/p_55_keV.h5
rcpann/ann_model/p_55_keV_2.h5
rcpann/ann_model/p_598_keV.h5
rcpann/ann_model/p_67_keV.h5
rcpann/ann_model/p_82_keV.h5
rcpann/ann_model/p_99_keV.h5
rcpann-0.0.7.dist-info/METADATA
rcpann-0.0.7.dist-info/WHEEL
rcpann-0.0.7.dist-info/top_level.txt
rcpann-0.0.7.dist-info/RECORD
